[
  {
    "label": "desktop_home",
    "viewport": "desktop",
    "path": "/",
    "url": "http://127.0.0.1:8765/",
    "status": 200,
    "load_ms": 1001,
    "isFragment": false,
    "fragment_reason": null,
    "axe_violations": [],
    "visual_issues": [
      {
        "id": "nav-density",
        "severity": "info",
        "item_count": 8,
        "nav_width": 886,
        "item_width_avg": 111
      }
    ]
  },
  {
    "label": "desktop_calendar",
    "viewport": "desktop",
    "path": "/calendar",
    "url": "http://127.0.0.1:8765/calendar",
    "status": 200,
    "load_ms": 879,
    "isFragment": false,
    "fragment_reason": null,
    "axe_violations": [],
    "visual_issues": [
      {
        "id": "nav-density",
        "severity": "info",
        "item_count": 8,
        "nav_width": 886,
        "item_width_avg": 111
      }
    ]
  },
  {
    "label": "desktop_search",
    "viewport": "desktop",
    "path": "/soldiers",
    "url": "http://127.0.0.1:8765/soldiers",
    "status": 200,
    "load_ms": 5851,
    "isFragment": false,
    "fragment_reason": null,
    "axe_violations": [],
    "visual_issues": [
      {
        "id": "unlabeled-input",
        "severity": "medium",
        "count": 15,
        "sample": [
          {
            "tag": "input",
            "name": "display_id",
            "type": "text"
          },
          {
            "tag": "select",
            "name": "entry_type",
            "type": "select-one"
          },
          {
            "tag": "input",
            "name": "record_type",
            "type": "text"
          },
          {
            "tag": "input",
            "name": "first_name",
            "type": "text"
          },
          {
            "tag": "input",
            "name": "middle_name",
            "type": "text"
          }
        ]
      },
      {
        "id": "nav-density",
        "severity": "info",
        "item_count": 8,
        "nav_width": 886,
        "item_width_avg": 111
      }
    ]
  },
  {
    "label": "desktop_browse",
    "viewport": "desktop",
    "path": "/browse",
    "url": "http://127.0.0.1:8765/browse",
    "status": 200,
    "load_ms": 1883,
    "isFragment": false,
    "fragment_reason": null,
    "axe_violations": [
      {
        "id": "label",
        "impact": "critical",
        "help": "Form elements must have labels",
        "helpUrl": "https://dequeuniversity.com/rules/axe/4.12/label?application=playwright",
        "nodes": 50,
        "sample": [
          [
            "input[data-browse-label=\"DXD-00001\"]"
          ],
          [
            "input[value=\"2\"]"
          ]
        ]
      },
      {
        "id": "select-name",
        "impact": "critical",
        "help": "Select element must have an accessible name",
        "helpUrl": "https://dequeuniversity.com/rules/axe/4.12/select-name?application=playwright",
        "nodes": 6,
        "sample": [
          [
            "select[name=\"scope\"]"
          ],
          [
            "select[name=\"sort\"]"
          ]
        ]
      }
    ],
    "visual_issues": [
      {
        "id": "small-tap-target",
        "severity": "medium",
        "count": 19,
        "sample": [
          {
            "tag": "a",
            "text": "Jasper Gray Turner A",
            "w": 142,
            "h": 16
          },
          {
            "tag": "a",
            "text": "Edward Allen Tate C",
            "w": 134,
            "h": 16
          },
          {
            "tag": "a",
            "text": "Thomas Clay Reed G",
            "w": 140,
            "h": 16
          },
          {
            "tag": "a",
            "text": "Robert Isaac Harper H",
            "w": 147,
            "h": 16
          },
          {
            "tag": "a",
            "text": "Robert Davis Reed J",
            "w": 136,
            "h": 16
          }
        ]
      },
      {
        "id": "unlabeled-input",
        "severity": "medium",
        "count": 56,
        "sample": [
          {
            "tag": "select",
            "name": "scope",
            "type": "select-one"
          },
          {
            "tag": "select",
            "name": "sort",
            "type": "select-one"
          },
          {
            "tag": "select",
            "name": "page_size",
            "type": "select-one"
          },
          {
            "tag": "select",
            "name": "entry_type",
            "type": "select-one"
          },
          {
            "tag": "select",
            "name": "review_status",
            "type": "select-one"
          }
        ]
      },
      {
        "id": "nav-density",
        "severity": "info",
        "item_count": 8,
        "nav_width": 886,
        "item_width_avg": 111
      },
      {
        "id": "table-rows",
        "severity": "info",
        "rows": 50,
        "page_height": 4369
      }
    ]
  },
  {
    "label": "desktop_review-queue",
    "viewport": "desktop",
    "path": "/review-queue",
    "url": "http://127.0.0.1:8765/review-queue",
    "status": 200,
    "load_ms": 797,
    "isFragment": false,
    "fragment_reason": null,
    "axe_violations": [],
    "visual_issues": [
      {
        "id": "nav-density",
        "severity": "info",
        "item_count": 8,
        "nav_width": 886,
        "item_width_avg": 111
      }
    ]
  },
  {
    "label": "desktop_insights",
    "viewport": "desktop",
    "path": "/insights",
    "url": "http://127.0.0.1:8765/insights",
    "status": 200,
    "load_ms": 1050,
    "isFragment": false,
    "fragment_reason": null,
    "axe_violations": [
      {
        "id": "select-name",
        "impact": "critical",
        "help": "Select element must have an accessible name",
        "helpUrl": "https://dequeuniversity.com/rules/axe/4.12/select-name?application=playwright",
        "nodes": 1,
        "sample": [
          [
            ".rounded-lg"
          ]
        ]
      }
    ],
    "visual_issues": [
      {
        "id": "unlabeled-input",
        "severity": "medium",
        "count": 1,
        "sample": [
          {
            "tag": "select",
            "name": "orientation",
            "type": "select-one"
          }
        ]
      },
      {
        "id": "nav-density",
        "severity": "info",
        "item_count": 8,
        "nav_width": 886,
        "item_width_avg": 111
      }
    ]
  },
  {
    "label": "desktop_share",
    "viewport": "desktop",
    "path": "/share",
    "url": "http://127.0.0.1:8765/share",
    "status": 200,
    "load_ms": 1090,
    "isFragment": false,
    "fragment_reason": null,
    "axe_violations": [],
    "visual_issues": [
      {
        "id": "nav-density",
        "severity": "info",
        "item_count": 8,
        "nav_width": 886,
        "item_width_avg": 111
      }
    ]
  },
  {
    "label": "desktop_settings",
    "viewport": "desktop",
    "path": "/settings",
    "url": "http://127.0.0.1:8765/settings",
    "status": 200,
    "load_ms": 1000,
    "isFragment": false,
    "fragment_reason": null,
    "axe_violations": [
      {
        "id": "label",
        "impact": "critical",
        "help": "Form elements must have labels",
        "helpUrl": "https://dequeuniversity.com/rules/axe/4.12/label?application=playwright",
        "nodes": 1,
        "sample": [
          [
            "input[name=\"confirmation_word\"]"
          ]
        ]
      }
    ],
    "visual_issues": [
      {
        "id": "unlabeled-input",
        "severity": "medium",
        "count": 1,
        "sample": [
          {
            "tag": "input",
            "name": "confirmation_word",
            "type": "text"
          }
        ]
      },
      {
        "id": "nav-density",
        "severity": "info",
        "item_count": 8,
        "nav_width": 886,
        "item_width_avg": 111
      }
    ]
  },
  {
    "label": "desktop_soldier-new",
    "viewport": "desktop",
    "path": "/soldiers/new",
    "url": "http://127.0.0.1:8765/soldiers/new",
    "status": 200,
    "load_ms": 1087,
    "isFragment": false,
    "fragment_reason": null,
    "axe_violations": [
      {
        "id": "label",
        "impact": "critical",
        "help": "Form elements must have labels",
        "helpUrl": "https://dequeuniversity.com/rules/axe/4.12/label?application=playwright",
        "nodes": 10,
        "sample": [
          [
            ".bg-slate-100"
          ],
          [
            "input[name=\"first_name\"]"
          ]
        ]
      },
      {
        "id": "nested-interactive",
        "impact": "serious",
        "help": "Interactive controls must not be nested",
        "helpUrl": "https://dequeuniversity.com/rules/axe/4.12/nested-interactive?application=playwright",
        "nodes": 1,
        "sample": [
          [
            "details > .items-start"
          ]
        ]
      },
      {
        "id": "select-name",
        "impact": "critical",
        "help": "Select element must have an accessible name",
        "helpUrl": "https://dequeuniversity.com/rules/axe/4.12/select-name?application=playwright",
        "nodes": 2,
        "sample": [
          [
            "select[name=\"entry_type\"]"
          ],
          [
            "select[name=\"confederate_home_status\"]"
          ]
        ]
      }
    ],
    "visual_issues": [
      {
        "id": "unlabeled-input",
        "severity": "medium",
        "count": 20,
        "sample": [
          {
            "tag": "input",
            "name": "display_id",
            "type": "text"
          },
          {
            "tag": "select",
            "name": "entry_type",
            "type": "select-one"
          },
          {
            "tag": "input",
            "name": "first_name",
            "type": "text"
          },
          {
            "tag": "input",
            "name": "middle_name",
            "type": "text"
          },
          {
            "tag": "input",
            "name": "last_name",
            "type": "text"
          }
        ]
      },
      {
        "id": "nav-density",
        "severity": "info",
        "item_count": 8,
        "nav_width": 886,
        "item_width_avg": 111
      }
    ]
  },
  {
    "label": "desktop_soldier-47",
    "viewport": "desktop",
    "path": "/soldiers/47",
    "url": "http://127.0.0.1:8765/soldiers/47",
    "status": 200,
    "load_ms": 1026,
    "isFragment": false,
    "fragment_reason": null,
    "axe_violations": [],
    "visual_issues": [
      {
        "id": "nav-density",
        "severity": "info",
        "item_count": 8,
        "nav_width": 886,
        "item_width_avg": 111
      }
    ]
  },
  {
    "label": "desktop_soldier-47-edit",
    "viewport": "desktop",
    "path": "/soldiers/47/edit",
    "url": "http://127.0.0.1:8765/soldiers/47/edit",
    "status": 200,
    "load_ms": 1106,
    "isFragment": false,
    "fragment_reason": null,
    "axe_violations": [
      {
        "id": "label",
        "impact": "critical",
        "help": "Form elements must have labels",
        "helpUrl": "https://dequeuniversity.com/rules/axe/4.12/label?application=playwright",
        "nodes": 10,
        "sample": [
          [
            "input[name=\"display_id\"]"
          ],
          [
            "input[name=\"first_name\"]"
          ]
        ]
      },
      {
        "id": "nested-interactive",
        "impact": "serious",
        "help": "Interactive controls must not be nested",
        "helpUrl": "https://dequeuniversity.com/rules/axe/4.12/nested-interactive?application=playwright",
        "nodes": 1,
        "sample": [
          [
            "details > .items-start"
          ]
        ]
      },
      {
        "id": "select-name",
        "impact": "critical",
        "help": "Select element must have an accessible name",
        "helpUrl": "https://dequeuniversity.com/rules/axe/4.12/select-name?application=playwright",
        "nodes": 2,
        "sample": [
          [
            "select[name=\"entry_type\"]"
          ],
          [
            "select[name=\"confederate_home_status\"]"
          ]
        ]
      }
    ],
    "visual_issues": [
      {
        "id": "unlabeled-input",
        "severity": "medium",
        "count": 20,
        "sample": [
          {
            "tag": "input",
            "name": "display_id",
            "type": "text"
          },
          {
            "tag": "select",
            "name": "entry_type",
            "type": "select-one"
          },
          {
            "tag": "input",
            "name": "first_name",
            "type": "text"
          },
          {
            "tag": "input",
            "name": "middle_name",
            "type": "text"
          },
          {
            "tag": "input",
            "name": "last_name",
            "type": "text"
          }
        ]
      },
      {
        "id": "nav-density",
        "severity": "info",
        "item_count": 8,
        "nav_width": 886,
        "item_width_avg": 111
      }
    ]
  },
  {
    "label": "desktop_soldier-35",
    "viewport": "desktop",
    "path": "/soldiers/35",
    "url": "http://127.0.0.1:8765/soldiers/35",
    "status": 200,
    "load_ms": 988,
    "isFragment": false,
    "fragment_reason": null,
    "axe_violations": [],
    "visual_issues": [
      {
        "id": "nav-density",
        "severity": "info",
        "item_count": 8,
        "nav_width": 886,
        "item_width_avg": 111
      }
    ]
  },
  {
    "label": "desktop_soldier-35-edit",
    "viewport": "desktop",
    "path": "/soldiers/35/edit",
    "url": "http://127.0.0.1:8765/soldiers/35/edit",
    "status": 200,
    "load_ms": 1084,
    "isFragment": false,
    "fragment_reason": null,
    "axe_violations": [
      {
        "id": "label",
        "impact": "critical",
        "help": "Form elements must have labels",
        "helpUrl": "https://dequeuniversity.com/rules/axe/4.12/label?application=playwright",
        "nodes": 10,
        "sample": [
          [
            "input[name=\"display_id\"]"
          ],
          [
            "input[name=\"first_name\"]"
          ]
        ]
      },
      {
        "id": "nested-interactive",
        "impact": "serious",
        "help": "Interactive controls must not be nested",
        "helpUrl": "https://dequeuniversity.com/rules/axe/4.12/nested-interactive?application=playwright",
        "nodes": 1,
        "sample": [
          [
            "details > .items-start"
          ]
        ]
      },
      {
        "id": "select-name",
        "impact": "critical",
        "help": "Select element must have an accessible name",
        "helpUrl": "https://dequeuniversity.com/rules/axe/4.12/select-name?application=playwright",
        "nodes": 2,
        "sample": [
          [
            "select[name=\"entry_type\"]"
          ],
          [
            "select[name=\"confederate_home_status\"]"
          ]
        ]
      }
    ],
    "visual_issues": [
      {
        "id": "unlabeled-input",
        "severity": "medium",
        "count": 23,
        "sample": [
          {
            "tag": "input",
            "name": "display_id",
            "type": "text"
          },
          {
            "tag": "select",
            "name": "entry_type",
            "type": "select-one"
          },
          {
            "tag": "input",
            "name": "first_name",
            "type": "text"
          },
          {
            "tag": "input",
            "name": "middle_name",
            "type": "text"
          },
          {
            "tag": "input",
            "name": "last_name",
            "type": "text"
          }
        ]
      },
      {
        "id": "nav-density",
        "severity": "info",
        "item_count": 8,
        "nav_width": 886,
        "item_width_avg": 111
      }
    ]
  },
  {
    "label": "tablet_home",
    "viewport": "tablet",
    "path": "/",
    "url": "http://127.0.0.1:8765/",
    "status": 200,
    "load_ms": 1015,
    "isFragment": false,
    "fragment_reason": null,
    "axe_violations": [],
    "visual_issues": [
      {
        "id": "nav-density",
        "severity": "info",
        "item_count": 8,
        "nav_width": 801,
        "item_width_avg": 100
      }
    ]
  },
  {
    "label": "tablet_calendar",
    "viewport": "tablet",
    "path": "/calendar",
    "url": "http://127.0.0.1:8765/calendar",
    "status": 200,
    "load_ms": 873,
    "isFragment": false,
    "fragment_reason": null,
    "axe_violations": [],
    "visual_issues": [
      {
        "id": "nav-density",
        "severity": "info",
        "item_count": 8,
        "nav_width": 801,
        "item_width_avg": 100
      }
    ]
  },
  {
    "label": "tablet_search",
    "viewport": "tablet",
    "path": "/soldiers",
    "url": "http://127.0.0.1:8765/soldiers",
    "status": 200,
    "load_ms": 5843,
    "isFragment": false,
    "fragment_reason": null,
    "axe_violations": [],
    "visual_issues": [
      {
        "id": "unlabeled-input",
        "severity": "medium",
        "count": 15,
        "sample": [
          {
            "tag": "input",
            "name": "display_id",
            "type": "text"
          },
          {
            "tag": "select",
            "name": "entry_type",
            "type": "select-one"
          },
          {
            "tag": "input",
            "name": "record_type",
            "type": "text"
          },
          {
            "tag": "input",
            "name": "first_name",
            "type": "text"
          },
          {
            "tag": "input",
            "name": "middle_name",
            "type": "text"
          }
        ]
      },
      {
        "id": "nav-density",
        "severity": "info",
        "item_count": 8,
        "nav_width": 801,
        "item_width_avg": 100
      }
    ]
  },
  {
    "label": "tablet_browse",
    "viewport": "tablet",
    "path": "/browse",
    "url": "http://127.0.0.1:8765/browse",
    "status": 200,
    "load_ms": 1858,
    "isFragment": false,
    "fragment_reason": null,
    "axe_violations": [
      {
        "id": "label",
        "impact": "critical",
        "help": "Form elements must have labels",
        "helpUrl": "https://dequeuniversity.com/rules/axe/4.12/label?application=playwright",
        "nodes": 50,
        "sample": [
          [
            "input[data-browse-label=\"DXD-00001\"]"
          ],
          [
            "input[value=\"2\"]"
          ]
        ]
      },
      {
        "id": "select-name",
        "impact": "critical",
        "help": "Select element must have an accessible name",
        "helpUrl": "https://dequeuniversity.com/rules/axe/4.12/select-name?application=playwright",
        "nodes": 6,
        "sample": [
          [
            "select[name=\"scope\"]"
          ],
          [
            "select[name=\"sort\"]"
          ]
        ]
      }
    ],
    "visual_issues": [
      {
        "id": "unlabeled-input",
        "severity": "medium",
        "count": 56,
        "sample": [
          {
            "tag": "select",
            "name": "scope",
            "type": "select-one"
          },
          {
            "tag": "select",
            "name": "sort",
            "type": "select-one"
          },
          {
            "tag": "select",
            "name": "page_size",
            "type": "select-one"
          },
          {
            "tag": "select",
            "name": "entry_type",
            "type": "select-one"
          },
          {
            "tag": "select",
            "name": "review_status",
            "type": "select-one"
          }
        ]
      },
      {
        "id": "nav-density",
        "severity": "info",
        "item_count": 8,
        "nav_width": 801,
        "item_width_avg": 100
      },
      {
        "id": "table-rows",
        "severity": "info",
        "rows": 50,
        "page_height": 6064
      }
    ]
  },
  {
    "label": "tablet_review-queue",
    "viewport": "tablet",
    "path": "/review-queue",
    "url": "http://127.0.0.1:8765/review-queue",
    "status": 200,
    "load_ms": 778,
    "isFragment": false,
    "fragment_reason": null,
    "axe_violations": [],
    "visual_issues": [
      {
        "id": "nav-density",
        "severity": "info",
        "item_count": 8,
        "nav_width": 801,
        "item_width_avg": 100
      }
    ]
  },
  {
    "label": "tablet_insights",
    "viewport": "tablet",
    "path": "/insights",
    "url": "http://127.0.0.1:8765/insights",
    "status": 200,
    "load_ms": 1027,
    "isFragment": false,
    "fragment_reason": null,
    "axe_violations": [
      {
        "id": "select-name",
        "impact": "critical",
        "help": "Select element must have an accessible name",
        "helpUrl": "https://dequeuniversity.com/rules/axe/4.12/select-name?application=playwright",
        "nodes": 1,
        "sample": [
          [
            ".rounded-lg"
          ]
        ]
      }
    ],
    "visual_issues": [
      {
        "id": "unlabeled-input",
        "severity": "medium",
        "count": 1,
        "sample": [
          {
            "tag": "select",
            "name": "orientation",
            "type": "select-one"
          }
        ]
      },
      {
        "id": "nav-density",
        "severity": "info",
        "item_count": 8,
        "nav_width": 801,
        "item_width_avg": 100
      }
    ]
  },
  {
    "label": "tablet_share",
    "viewport": "tablet",
    "path": "/share",
    "url": "http://127.0.0.1:8765/share",
    "status": 200,
    "load_ms": 1046,
    "isFragment": false,
    "fragment_reason": null,
    "axe_violations": [],
    "visual_issues": [
      {
        "id": "nav-density",
        "severity": "info",
        "item_count": 8,
        "nav_width": 801,
        "item_width_avg": 100
      }
    ]
  },
  {
    "label": "tablet_settings",
    "viewport": "tablet",
    "path": "/settings",
    "url": "http://127.0.0.1:8765/settings",
    "status": 200,
    "load_ms": 935,
    "isFragment": false,
    "fragment_reason": null,
    "axe_violations": [
      {
        "id": "label",
        "impact": "critical",
        "help": "Form elements must have labels",
        "helpUrl": "https://dequeuniversity.com/rules/axe/4.12/label?application=playwright",
        "nodes": 1,
        "sample": [
          [
            "input[name=\"confirmation_word\"]"
          ]
        ]
      }
    ],
    "visual_issues": [
      {
        "id": "unlabeled-input",
        "severity": "medium",
        "count": 1,
        "sample": [
          {
            "tag": "input",
            "name": "confirmation_word",
            "type": "text"
          }
        ]
      },
      {
        "id": "nav-density",
        "severity": "info",
        "item_count": 8,
        "nav_width": 801,
        "item_width_avg": 100
      }
    ]
  },
  {
    "label": "tablet_soldier-new",
    "viewport": "tablet",
    "path": "/soldiers/new",
    "url": "http://127.0.0.1:8765/soldiers/new",
    "status": 200,
    "load_ms": 1015,
    "isFragment": false,
    "fragment_reason": null,
    "axe_violations": [
      {
        "id": "label",
        "impact": "critical",
        "help": "Form elements must have labels",
        "helpUrl": "https://dequeuniversity.com/rules/axe/4.12/label?application=playwright",
        "nodes": 10,
        "sample": [
          [
            ".bg-slate-100"
          ],
          [
            "input[name=\"first_name\"]"
          ]
        ]
      },
      {
        "id": "nested-interactive",
        "impact": "serious",
        "help": "Interactive controls must not be nested",
        "helpUrl": "https://dequeuniversity.com/rules/axe/4.12/nested-interactive?application=playwright",
        "nodes": 1,
        "sample": [
          [
            "details > .items-start"
          ]
        ]
      },
      {
        "id": "select-name",
        "impact": "critical",
        "help": "Select element must have an accessible name",
        "helpUrl": "https://dequeuniversity.com/rules/axe/4.12/select-name?application=playwright",
        "nodes": 2,
        "sample": [
          [
            "select[name=\"entry_type\"]"
          ],
          [
            "select[name=\"confederate_home_status\"]"
          ]
        ]
      }
    ],
    "visual_issues": [
      {
        "id": "unlabeled-input",
        "severity": "medium",
        "count": 20,
        "sample": [
          {
            "tag": "input",
            "name": "display_id",
            "type": "text"
          },
          {
            "tag": "select",
            "name": "entry_type",
            "type": "select-one"
          },
          {
            "tag": "input",
            "name": "first_name",
            "type": "text"
          },
          {
            "tag": "input",
            "name": "middle_name",
            "type": "text"
          },
          {
            "tag": "input",
            "name": "last_name",
            "type": "text"
          }
        ]
      },
      {
        "id": "nav-density",
        "severity": "info",
        "item_count": 8,
        "nav_width": 801,
        "item_width_avg": 100
      }
    ]
  },
  {
    "label": "tablet_soldier-47",
    "viewport": "tablet",
    "path": "/soldiers/47",
    "url": "http://127.0.0.1:8765/soldiers/47",
    "status": 200,
    "load_ms": 1024,
    "isFragment": false,
    "fragment_reason": null,
    "axe_violations": [],
    "visual_issues": [
      {
        "id": "overflow-x",
        "severity": "high",
        "count": 20,
        "sample": [
          {
            "tag": "form",
            "id": null,
            "cls": "absolute left-0 z-20 mt-3 w-[min(24rem,calc(100vw-3rem))] rounded-2xl border bor",
            "right": 1045,
            "width": 384
          },
          {
            "tag": "div",
            "id": null,
            "cls": "flex items-start justify-between gap-3",
            "right": 1028,
            "width": 350
          },
          {
            "tag": "details",
            "id": null,
            "cls": "relative",
            "right": 1028,
            "width": 32
          },
          {
            "tag": "summary",
            "id": null,
            "cls": "inline-flex h-8 w-8 cursor-pointer items-center justify-center rounded-full bord",
            "right": 1028,
            "width": 32
          },
          {
            "tag": "div",
            "id": null,
            "cls": "absolute right-0 z-10 mt-2 w-72 rounded-2xl border border-[rgba(141,116,64,0.28)",
            "right": 1028,
            "width": 288
          }
        ]
      },
      {
        "id": "nav-density",
        "severity": "info",
        "item_count": 8,
        "nav_width": 801,
        "item_width_avg": 100
      }
    ]
  },
  {
    "label": "tablet_soldier-47-edit",
    "viewport": "tablet",
    "path": "/soldiers/47/edit",
    "url": "http://127.0.0.1:8765/soldiers/47/edit",
    "status": 200,
    "load_ms": 1003,
    "isFragment": false,
    "fragment_reason": null,
    "axe_violations": [
      {
        "id": "label",
        "impact": "critical",
        "help": "Form elements must have labels",
        "helpUrl": "https://dequeuniversity.com/rules/axe/4.12/label?application=playwright",
        "nodes": 10,
        "sample": [
          [
            "input[name=\"display_id\"]"
          ],
          [
            "input[name=\"first_name\"]"
          ]
        ]
      },
      {
        "id": "nested-interactive",
        "impact": "serious",
        "help": "Interactive controls must not be nested",
        "helpUrl": "https://dequeuniversity.com/rules/axe/4.12/nested-interactive?application=playwright",
        "nodes": 1,
        "sample": [
          [
            "details > .items-start"
          ]
        ]
      },
      {
        "id": "select-name",
        "impact": "critical",
        "help": "Select element must have an accessible name",
        "helpUrl": "https://dequeuniversity.com/rules/axe/4.12/select-name?application=playwright",
        "nodes": 2,
        "sample": [
          [
            "select[name=\"entry_type\"]"
          ],
          [
            "select[name=\"confederate_home_status\"]"
          ]
        ]
      }
    ],
    "visual_issues": [
      {
        "id": "unlabeled-input",
        "severity": "medium",
        "count": 20,
        "sample": [
          {
            "tag": "input",
            "name": "display_id",
            "type": "text"
          },
          {
            "tag": "select",
            "name": "entry_type",
            "type": "select-one"
          },
          {
            "tag": "input",
            "name": "first_name",
            "type": "text"
          },
          {
            "tag": "input",
            "name": "middle_name",
            "type": "text"
          },
          {
            "tag": "input",
            "name": "last_name",
            "type": "text"
          }
        ]
      },
      {
        "id": "nav-density",
        "severity": "info",
        "item_count": 8,
        "nav_width": 801,
        "item_width_avg": 100
      }
    ]
  },
  {
    "label": "tablet_soldier-35",
    "viewport": "tablet",
    "path": "/soldiers/35",
    "url": "http://127.0.0.1:8765/soldiers/35",
    "status": 200,
    "load_ms": 956,
    "isFragment": false,
    "fragment_reason": null,
    "axe_violations": [],
    "visual_issues": [
      {
        "id": "overflow-x",
        "severity": "high",
        "count": 20,
        "sample": [
          {
            "tag": "form",
            "id": null,
            "cls": "absolute left-0 z-20 mt-3 w-[min(24rem,calc(100vw-3rem))] rounded-2xl border bor",
            "right": 1045,
            "width": 384
          },
          {
            "tag": "div",
            "id": null,
            "cls": "flex items-start justify-between gap-3",
            "right": 1028,
            "width": 350
          },
          {
            "tag": "details",
            "id": null,
            "cls": "relative",
            "right": 1028,
            "width": 32
          },
          {
            "tag": "summary",
            "id": null,
            "cls": "inline-flex h-8 w-8 cursor-pointer items-center justify-center rounded-full bord",
            "right": 1028,
            "width": 32
          },
          {
            "tag": "div",
            "id": null,
            "cls": "absolute right-0 z-10 mt-2 w-72 rounded-2xl border border-[rgba(141,116,64,0.28)",
            "right": 1028,
            "width": 288
          }
        ]
      },
      {
        "id": "nav-density",
        "severity": "info",
        "item_count": 8,
        "nav_width": 801,
        "item_width_avg": 100
      }
    ]
  },
  {
    "label": "tablet_soldier-35-edit",
    "viewport": "tablet",
    "path": "/soldiers/35/edit",
    "url": "http://127.0.0.1:8765/soldiers/35/edit",
    "status": 200,
    "load_ms": 1013,
    "isFragment": false,
    "fragment_reason": null,
    "axe_violations": [
      {
        "id": "label",
        "impact": "critical",
        "help": "Form elements must have labels",
        "helpUrl": "https://dequeuniversity.com/rules/axe/4.12/label?application=playwright",
        "nodes": 10,
        "sample": [
          [
            "input[name=\"display_id\"]"
          ],
          [
            "input[name=\"first_name\"]"
          ]
        ]
      },
      {
        "id": "nested-interactive",
        "impact": "serious",
        "help": "Interactive controls must not be nested",
        "helpUrl": "https://dequeuniversity.com/rules/axe/4.12/nested-interactive?application=playwright",
        "nodes": 1,
        "sample": [
          [
            "details > .items-start"
          ]
        ]
      },
      {
        "id": "select-name",
        "impact": "critical",
        "help": "Select element must have an accessible name",
        "helpUrl": "https://dequeuniversity.com/rules/axe/4.12/select-name?application=playwright",
        "nodes": 2,
        "sample": [
          [
            "select[name=\"entry_type\"]"
          ],
          [
            "select[name=\"confederate_home_status\"]"
          ]
        ]
      }
    ],
    "visual_issues": [
      {
        "id": "unlabeled-input",
        "severity": "medium",
        "count": 23,
        "sample": [
          {
            "tag": "input",
            "name": "display_id",
            "type": "text"
          },
          {
            "tag": "select",
            "name": "entry_type",
            "type": "select-one"
          },
          {
            "tag": "input",
            "name": "first_name",
            "type": "text"
          },
          {
            "tag": "input",
            "name": "middle_name",
            "type": "text"
          },
          {
            "tag": "input",
            "name": "last_name",
            "type": "text"
          }
        ]
      },
      {
        "id": "nav-density",
        "severity": "info",
        "item_count": 8,
        "nav_width": 801,
        "item_width_avg": 100
      }
    ]
  },
  {
    "label": "mobile_home",
    "viewport": "mobile",
    "path": "/",
    "url": "http://127.0.0.1:8765/",
    "status": 200,
    "load_ms": 987,
    "isFragment": false,
    "fragment_reason": null,
    "axe_violations": [],
    "visual_issues": [
      {
        "id": "nav-density",
        "severity": "info",
        "item_count": 8,
        "nav_width": 324,
        "item_width_avg": 41
      }
    ]
  },
  {
    "label": "mobile_calendar",
    "viewport": "mobile",
    "path": "/calendar",
    "url": "http://127.0.0.1:8765/calendar",
    "status": 200,
    "load_ms": 884,
    "isFragment": false,
    "fragment_reason": null,
    "axe_violations": [],
    "visual_issues": [
      {
        "id": "nav-density",
        "severity": "info",
        "item_count": 8,
        "nav_width": 324,
        "item_width_avg": 41
      }
    ]
  },
  {
    "label": "mobile_search",
    "viewport": "mobile",
    "path": "/soldiers",
    "url": "http://127.0.0.1:8765/soldiers",
    "status": 200,
    "load_ms": 5823,
    "isFragment": false,
    "fragment_reason": null,
    "axe_violations": [],
    "visual_issues": [
      {
        "id": "unlabeled-input",
        "severity": "medium",
        "count": 15,
        "sample": [
          {
            "tag": "input",
            "name": "display_id",
            "type": "text"
          },
          {
            "tag": "select",
            "name": "entry_type",
            "type": "select-one"
          },
          {
            "tag": "input",
            "name": "record_type",
            "type": "text"
          },
          {
            "tag": "input",
            "name": "first_name",
            "type": "text"
          },
          {
            "tag": "input",
            "name": "middle_name",
            "type": "text"
          }
        ]
      },
      {
        "id": "nav-density",
        "severity": "info",
        "item_count": 8,
        "nav_width": 324,
        "item_width_avg": 41
      }
    ]
  },
  {
    "label": "mobile_browse",
    "viewport": "mobile",
    "path": "/browse",
    "url": "http://127.0.0.1:8765/browse",
    "status": 200,
    "load_ms": 1443,
    "isFragment": false,
    "fragment_reason": null,
    "axe_violations": [
      {
        "id": "label",
        "impact": "critical",
        "help": "Form elements must have labels",
        "helpUrl": "https://dequeuniversity.com/rules/axe/4.12/label?application=playwright",
        "nodes": 50,
        "sample": [
          [
            "input[data-browse-label=\"DXD-00001\"]"
          ],
          [
            "input[value=\"2\"]"
          ]
        ]
      },
      {
        "id": "select-name",
        "impact": "critical",
        "help": "Select element must have an accessible name",
        "helpUrl": "https://dequeuniversity.com/rules/axe/4.12/select-name?application=playwright",
        "nodes": 6,
        "sample": [
          [
            "select[name=\"scope\"]"
          ],
          [
            "select[name=\"sort\"]"
          ]
        ]
      }
    ],
    "visual_issues": [
      {
        "id": "overflow-x",
        "severity": "high",
        "count": 309,
        "sample": [
          {
            "tag": "table",
            "id": null,
            "cls": "min-w-full border-collapse text-sm",
            "right": 868,
            "width": 854
          },
          {
            "tag": "thead",
            "id": null,
            "cls": "bg-[rgba(36,48,61,0.92)] text-left text-[#f2ede1]",
            "right": 868,
            "width": 854
          },
          {
            "tag": "tr",
            "id": null,
            "cls": "",
            "right": 868,
            "width": 854
          },
          {
            "tag": "th",
            "id": null,
            "cls": "px-4 py-3 font-semibold uppercase tracking-[0.18em] text-xs",
            "right": 486,
            "width": 97
          },
          {
            "tag": "tbody",
            "id": null,
            "cls": "",
            "right": 868,
            "width": 854
          }
        ]
      },
      {
        "id": "unlabeled-input",
        "severity": "medium",
        "count": 56,
        "sample": [
          {
            "tag": "select",
            "name": "scope",
            "type": "select-one"
          },
          {
            "tag": "select",
            "name": "sort",
            "type": "select-one"
          },
          {
            "tag": "select",
            "name": "page_size",
            "type": "select-one"
          },
          {
            "tag": "select",
            "name": "entry_type",
            "type": "select-one"
          },
          {
            "tag": "select",
            "name": "review_status",
            "type": "select-one"
          }
        ]
      },
      {
        "id": "nav-density",
        "severity": "info",
        "item_count": 8,
        "nav_width": 324,
        "item_width_avg": 41
      },
      {
        "id": "table-rows",
        "severity": "info",
        "rows": 50,
        "page_height": 6792
      }
    ]
  },
  {
    "label": "mobile_review-queue",
    "viewport": "mobile",
    "path": "/review-queue",
    "url": "http://127.0.0.1:8765/review-queue",
    "status": 200,
    "load_ms": 773,
    "isFragment": false,
    "fragment_reason": null,
    "axe_violations": [],
    "visual_issues": [
      {
        "id": "nav-density",
        "severity": "info",
        "item_count": 8,
        "nav_width": 324,
        "item_width_avg": 41
      }
    ]
  },
  {
    "label": "mobile_insights",
    "viewport": "mobile",
    "path": "/insights",
    "url": "http://127.0.0.1:8765/insights",
    "status": 200,
    "load_ms": 992,
    "isFragment": false,
    "fragment_reason": null,
    "axe_violations": [
      {
        "id": "select-name",
        "impact": "critical",
        "help": "Select element must have an accessible name",
        "helpUrl": "https://dequeuniversity.com/rules/axe/4.12/select-name?application=playwright",
        "nodes": 1,
        "sample": [
          [
            ".rounded-lg"
          ]
        ]
      }
    ],
    "visual_issues": [
      {
        "id": "unlabeled-input",
        "severity": "medium",
        "count": 1,
        "sample": [
          {
            "tag": "select",
            "name": "orientation",
            "type": "select-one"
          }
        ]
      },
      {
        "id": "nav-density",
        "severity": "info",
        "item_count": 8,
        "nav_width": 324,
        "item_width_avg": 41
      }
    ]
  },
  {
    "label": "mobile_share",
    "viewport": "mobile",
    "path": "/share",
    "url": "http://127.0.0.1:8765/share",
    "status": 200,
    "load_ms": 1003,
    "isFragment": false,
    "fragment_reason": null,
    "axe_violations": [],
    "visual_issues": [
      {
        "id": "nav-density",
        "severity": "info",
        "item_count": 8,
        "nav_width": 324,
        "item_width_avg": 41
      }
    ]
  },
  {
    "label": "mobile_settings",
    "viewport": "mobile",
    "path": "/settings",
    "url": "http://127.0.0.1:8765/settings",
    "status": 200,
    "load_ms": 861,
    "isFragment": false,
    "fragment_reason": null,
    "axe_violations": [
      {
        "id": "label",
        "impact": "critical",
        "help": "Form elements must have labels",
        "helpUrl": "https://dequeuniversity.com/rules/axe/4.12/label?application=playwright",
        "nodes": 1,
        "sample": [
          [
            "input[name=\"confirmation_word\"]"
          ]
        ]
      }
    ],
    "visual_issues": [
      {
        "id": "unlabeled-input",
        "severity": "medium",
        "count": 1,
        "sample": [
          {
            "tag": "input",
            "name": "confirmation_word",
            "type": "text"
          }
        ]
      },
      {
        "id": "nav-density",
        "severity": "info",
        "item_count": 8,
        "nav_width": 324,
        "item_width_avg": 41
      }
    ]
  },
  {
    "label": "mobile_soldier-new",
    "viewport": "mobile",
    "path": "/soldiers/new",
    "url": "http://127.0.0.1:8765/soldiers/new",
    "status": 200,
    "load_ms": 1039,
    "isFragment": false,
    "fragment_reason": null,
    "axe_violations": [
      {
        "id": "label",
        "impact": "critical",
        "help": "Form elements must have labels",
        "helpUrl": "https://dequeuniversity.com/rules/axe/4.12/label?application=playwright",
        "nodes": 10,
        "sample": [
          [
            ".bg-slate-100"
          ],
          [
            "input[name=\"first_name\"]"
          ]
        ]
      },
      {
        "id": "nested-interactive",
        "impact": "serious",
        "help": "Interactive controls must not be nested",
        "helpUrl": "https://dequeuniversity.com/rules/axe/4.12/nested-interactive?application=playwright",
        "nodes": 1,
        "sample": [
          [
            "details > .items-start"
          ]
        ]
      },
      {
        "id": "select-name",
        "impact": "critical",
        "help": "Select element must have an accessible name",
        "helpUrl": "https://dequeuniversity.com/rules/axe/4.12/select-name?application=playwright",
        "nodes": 2,
        "sample": [
          [
            "select[name=\"entry_type\"]"
          ],
          [
            "select[name=\"confederate_home_status\"]"
          ]
        ]
      }
    ],
    "visual_issues": [
      {
        "id": "unlabeled-input",
        "severity": "medium",
        "count": 20,
        "sample": [
          {
            "tag": "input",
            "name": "display_id",
            "type": "text"
          },
          {
            "tag": "select",
            "name": "entry_type",
            "type": "select-one"
          },
          {
            "tag": "input",
            "name": "first_name",
            "type": "text"
          },
          {
            "tag": "input",
            "name": "middle_name",
            "type": "text"
          },
          {
            "tag": "input",
            "name": "last_name",
            "type": "text"
          }
        ]
      },
      {
        "id": "nav-density",
        "severity": "info",
        "item_count": 8,
        "nav_width": 324,
        "item_width_avg": 41
      }
    ]
  },
  {
    "label": "mobile_soldier-47",
    "viewport": "mobile",
    "path": "/soldiers/47",
    "url": "http://127.0.0.1:8765/soldiers/47",
    "status": 200,
    "load_ms": 990,
    "isFragment": false,
    "fragment_reason": null,
    "axe_violations": [],
    "visual_issues": [
      {
        "id": "nav-density",
        "severity": "info",
        "item_count": 8,
        "nav_width": 324,
        "item_width_avg": 41
      }
    ]
  },
  {
    "label": "mobile_soldier-47-edit",
    "viewport": "mobile",
    "path": "/soldiers/47/edit",
    "url": "http://127.0.0.1:8765/soldiers/47/edit",
    "status": 200,
    "load_ms": 987,
    "isFragment": false,
    "fragment_reason": null,
    "axe_violations": [
      {
        "id": "label",
        "impact": "critical",
        "help": "Form elements must have labels",
        "helpUrl": "https://dequeuniversity.com/rules/axe/4.12/label?application=playwright",
        "nodes": 10,
        "sample": [
          [
            "input[name=\"display_id\"]"
          ],
          [
            "input[name=\"first_name\"]"
          ]
        ]
      },
      {
        "id": "nested-interactive",
        "impact": "serious",
        "help": "Interactive controls must not be nested",
        "helpUrl": "https://dequeuniversity.com/rules/axe/4.12/nested-interactive?application=playwright",
        "nodes": 1,
        "sample": [
          [
            "details > .items-start"
          ]
        ]
      },
      {
        "id": "select-name",
        "impact": "critical",
        "help": "Select element must have an accessible name",
        "helpUrl": "https://dequeuniversity.com/rules/axe/4.12/select-name?application=playwright",
        "nodes": 2,
        "sample": [
          [
            "select[name=\"entry_type\"]"
          ],
          [
            "select[name=\"confederate_home_status\"]"
          ]
        ]
      }
    ],
    "visual_issues": [
      {
        "id": "unlabeled-input",
        "severity": "medium",
        "count": 20,
        "sample": [
          {
            "tag": "input",
            "name": "display_id",
            "type": "text"
          },
          {
            "tag": "select",
            "name": "entry_type",
            "type": "select-one"
          },
          {
            "tag": "input",
            "name": "first_name",
            "type": "text"
          },
          {
            "tag": "input",
            "name": "middle_name",
            "type": "text"
          },
          {
            "tag": "input",
            "name": "last_name",
            "type": "text"
          }
        ]
      },
      {
        "id": "nav-density",
        "severity": "info",
        "item_count": 8,
        "nav_width": 324,
        "item_width_avg": 41
      }
    ]
  },
  {
    "label": "mobile_soldier-35",
    "viewport": "mobile",
    "path": "/soldiers/35",
    "url": "http://127.0.0.1:8765/soldiers/35",
    "status": 200,
    "load_ms": 925,
    "isFragment": false,
    "fragment_reason": null,
    "axe_violations": [],
    "visual_issues": [
      {
        "id": "nav-density",
        "severity": "info",
        "item_count": 8,
        "nav_width": 324,
        "item_width_avg": 41
      }
    ]
  },
  {
    "label": "mobile_soldier-35-edit",
    "viewport": "mobile",
    "path": "/soldiers/35/edit",
    "url": "http://127.0.0.1:8765/soldiers/35/edit",
    "status": 200,
    "load_ms": 981,
    "isFragment": false,
    "fragment_reason": null,
    "axe_violations": [
      {
        "id": "label",
        "impact": "critical",
        "help": "Form elements must have labels",
        "helpUrl": "https://dequeuniversity.com/rules/axe/4.12/label?application=playwright",
        "nodes": 10,
        "sample": [
          [
            "input[name=\"display_id\"]"
          ],
          [
            "input[name=\"first_name\"]"
          ]
        ]
      },
      {
        "id": "nested-interactive",
        "impact": "serious",
        "help": "Interactive controls must not be nested",
        "helpUrl": "https://dequeuniversity.com/rules/axe/4.12/nested-interactive?application=playwright",
        "nodes": 1,
        "sample": [
          [
            "details > .items-start"
          ]
        ]
      },
      {
        "id": "select-name",
        "impact": "critical",
        "help": "Select element must have an accessible name",
        "helpUrl": "https://dequeuniversity.com/rules/axe/4.12/select-name?application=playwright",
        "nodes": 2,
        "sample": [
          [
            "select[name=\"entry_type\"]"
          ],
          [
            "select[name=\"confederate_home_status\"]"
          ]
        ]
      }
    ],
    "visual_issues": [
      {
        "id": "unlabeled-input",
        "severity": "medium",
        "count": 23,
        "sample": [
          {
            "tag": "input",
            "name": "display_id",
            "type": "text"
          },
          {
            "tag": "select",
            "name": "entry_type",
            "type": "select-one"
          },
          {
            "tag": "input",
            "name": "first_name",
            "type": "text"
          },
          {
            "tag": "input",
            "name": "middle_name",
            "type": "text"
          },
          {
            "tag": "input",
            "name": "last_name",
            "type": "text"
          }
        ]
      },
      {
        "id": "nav-density",
        "severity": "info",
        "item_count": 8,
        "nav_width": 324,
        "item_width_avg": 41
      }
    ]
  }
]